trml2pdf/__init__.py
trml2pdf/color.py
trml2pdf/trml2pdf.py
trml2pdf/utils.py
djangoplicity_trml2pdf-1.0.dist-info/LICENSE.txt
djangoplicity_trml2pdf-1.0.dist-info/METADATA
djangoplicity_trml2pdf-1.0.dist-info/WHEEL
djangoplicity_trml2pdf-1.0.dist-info/top_level.txt
djangoplicity_trml2pdf-1.0.dist-info/RECORD
