Metadata-Version: 2.1
Name: djangoplicity-trml2pdf
Version: 1.0
Summary: Tiny RML2PDF is a tool to easily create PDF document without programming.
Home-page: https://github.com/djangoplicity/djangoplicity-trml2pdf
Author: Fabien Pinckaers
Author-email: fp@tiny.be
License: LGPL
Download-URL: https://github.com/djangoplicity/djangoplicity-trml2pdf/archive/refs/tags/1.0.tar.gz
Platform: UNKNOWN
License-File: LICENSE.txt
